<?xml version="1.0" encoding="utf-8"?>
<CalendarMap xmlns:xsi="http://www.w3.org/2001/XMLSchema-instance" xmlns:xsd="http://www.w3.org/2001/XMLSchema">
  <days>
    <item>
      <key>
        <string>2-12-19-2023</string>
      </key>
      <value>
        <DayNotes>
          <Exists>false</Exists>
          <DayQuality>0</DayQuality>
          <SleepQuality>0</SleepQuality>
          <TookMeds>false</TookMeds>
        </DayNotes>
      </value>
    </item>
    <item>
      <key>
        <string>3-12-20-2023</string>
      </key>
      <value>
        <DayNotes>
          <Exists>true</Exists>
          <DayQuality>8</DayQuality>
          <SleepQuality>6</SleepQuality>
          <TookMeds>false</TookMeds>
        </DayNotes>
      </value>
    </item>
    <item>
      <key>
        <string>4-12-21-2023</string>
      </key>
      <value>
        <DayNotes>
          <Exists>true</Exists>
          <DayQuality>8</DayQuality>
          <SleepQuality>9</SleepQuality>
          <TookMeds>true</TookMeds>
        </DayNotes>
      </value>
    </item>
    <item>
      <key>
        <string>5-12-22-2023</string>
      </key>
      <value>
        <DayNotes>
          <Exists>true</Exists>
          <DayQuality>6</DayQuality>
          <SleepQuality>10</SleepQuality>
          <TookMeds>false</TookMeds>
        </DayNotes>
      </value>
    </item>
    <item>
      <key>
        <string>6-12-23-2023</string>
      </key>
      <value>
        <DayNotes>
          <Exists>true</Exists>
          <DayQuality>8</DayQuality>
          <SleepQuality>10</SleepQuality>
          <TookMeds>false</TookMeds>
        </DayNotes>
      </value>
    </item>
  </days>
</CalendarMap>